mlstclassifier_cd/KNN_model_061223.sav
mlstclassifier_cd/MLST_classifier_EB.py
mlstclassifier_cd/MLST_classifier_KNN_061223.py
mlstclassifier_cd/__init__.py
mlstclassifier_cd-0.4.3.dist-info/LICENSE
mlstclassifier_cd-0.4.3.dist-info/METADATA
mlstclassifier_cd-0.4.3.dist-info/WHEEL
mlstclassifier_cd-0.4.3.dist-info/entry_points.txt
mlstclassifier_cd-0.4.3.dist-info/RECORD
