Metadata-Version: 2.1
Name: mlstclassifier_cd
Version: 0.4.3
Summary: multi-locus sequence type clade classifier for C.difficile
Home-page: https://github.com/eliottBo/MLSTclassifier_cd
License: Apache License
Author: Eliott Bosshard
Requires-Python: >=3.11,<3.12
Classifier: License :: Other/Proprietary License
Classifier: Programming Language :: Python :: 3
Classifier: Programming Language :: Python :: 3.11
Requires-Dist: joblib (>=1.2.0,<=1.3.2)
Requires-Dist: matplotlib (>=3.7.0)
Requires-Dist: numpy (==1.24.3)
Requires-Dist: pandas (>=1.5.3)
Requires-Dist: plotly (>=5.15.0)
Requires-Dist: scikit-learn (==1.3.0)
Project-URL: Repository, https://github.com/eliottBo/MLSTclassifier_cd
